abstract_http_client/__init__.py
abstract_http_client/exceptions.py
abstract_http_client/http_clients/__init__.py
abstract_http_client/http_clients/http_client_base.py
abstract_http_client/http_clients/requests_client.py
abstract_http_client/http_services/__init__.py
abstract_http_client/http_services/constants.py
abstract_http_client/http_services/http_service_base.py
abstract_http_client/http_services/requests_service.py
abstract_http_client-1.0.3.dist-info/LICENSE
abstract_http_client-1.0.3.dist-info/METADATA
abstract_http_client-1.0.3.dist-info/WHEEL
abstract_http_client-1.0.3.dist-info/top_level.txt
abstract_http_client-1.0.3.dist-info/RECORD
