Metadata-Version: 2.1
Name: abstract-http-client
Version: 1.0.3
Summary: Abstract Base Class for writing Requests based Rest Api Clients
Home-page: https://github.com/QualiSystemsLab/abstract-http-client
Author: QualiLab
Author-email: support@qualisystems.com
License: MIT
Platform: UNKNOWN
Classifier: Programming Language :: Python :: 3.7
Classifier: License :: OSI Approved :: MIT License
Classifier: Operating System :: OS Independent
Requires-Python: >=3.7
License-File: LICENSE
Requires-Dist: requests (<3,>=2)
